MANIFEST.in
README.md
meta.json
setup.py
eng_spacysentiment/__init__.py
eng_spacysentiment/meta.json
eng_spacysentiment.egg-info/PKG-INFO
eng_spacysentiment.egg-info/SOURCES.txt
eng_spacysentiment.egg-info/dependency_links.txt
eng_spacysentiment.egg-info/entry_points.txt
eng_spacysentiment.egg-info/not-zip-safe
eng_spacysentiment.egg-info/requires.txt
eng_spacysentiment.egg-info/top_level.txt
eng_spacysentiment/eng_spacysentiment-2.3.0/README.md
eng_spacysentiment/eng_spacysentiment-2.3.0/config.cfg
eng_spacysentiment/eng_spacysentiment-2.3.0/meta.json
eng_spacysentiment/eng_spacysentiment-2.3.0/tokenizer
eng_spacysentiment/eng_spacysentiment-2.3.0/textcat/cfg
eng_spacysentiment/eng_spacysentiment-2.3.0/textcat/model
eng_spacysentiment/eng_spacysentiment-2.3.0/vocab/key2row
eng_spacysentiment/eng_spacysentiment-2.3.0/vocab/lookups.bin
eng_spacysentiment/eng_spacysentiment-2.3.0/vocab/strings.json
eng_spacysentiment/eng_spacysentiment-2.3.0/vocab/vectors
eng_spacysentiment/eng_spacysentiment-2.3.0/vocab/vectors.cfg