Metadata-Version: 2.1
Name: eng-spacysentiment
Version: 2.3.0
Summary: sentiment analysis using spacy pipelines
Home-page: https://github.com/Vishnunkumar/eng_spacysentiment
Author: Vishnu
Author-email: vishnunkumar25@gmail.com
License: MIT
